hellopackage/__init__.py
hellopackage/hello.py
helloworld1609-0.0.1.dist-info/LICENSE
helloworld1609-0.0.1.dist-info/METADATA
helloworld1609-0.0.1.dist-info/WHEEL
helloworld1609-0.0.1.dist-info/top_level.txt
helloworld1609-0.0.1.dist-info/RECORD
